mister_webhooks/__init__.py
mister_webhooks/client.py
mister_webhooks/connection_profile.py
mister_webhooks/ssl_cert.py
mister_webhooks/types.py
mister_webhooks/webhook_event.py
mister_webhooks-1.0.0.dist-info/METADATA
mister_webhooks-1.0.0.dist-info/WHEEL
mister_webhooks-1.0.0.dist-info/licenses/LICENSE
mister_webhooks-1.0.0.dist-info/RECORD
